pyrssi/__init__.py
pyrssi/rssi.py
pyrssi-0.1.1.dist-info/licenses/LICENSE
pyrssi-0.1.1.dist-info/METADATA
pyrssi-0.1.1.dist-info/WHEEL
pyrssi-0.1.1.dist-info/top_level.txt
pyrssi-0.1.1.dist-info/RECORD
