Metadata-Version: 2.4
Name: pyrssi
Version: 0.1.1
Summary: Get Wi-Fi RSSI on Mac, Windows, or Linux
Home-page: https://github.com/ericdennis7/pyrssi
Author: Eric Dennis
License: MIT
Classifier: Programming Language :: Python :: 3
Classifier: Operating System :: MacOS :: MacOS X
Classifier: Operating System :: Microsoft :: Windows
Classifier: Operating System :: POSIX :: Linux
Requires-Python: >=3.7
License-File: LICENSE
Requires-Dist: pyobjc; platform_system == "Darwin"
Dynamic: author
Dynamic: classifier
Dynamic: description
Dynamic: description-content-type
Dynamic: home-page
Dynamic: license
Dynamic: license-file
Dynamic: requires-dist
Dynamic: requires-python
Dynamic: summary
